python_strip_whitespace/__init__.py
python_strip_whitespace/functions/regex.py
python_strip_whitespace/functions/regex_patterns/__init__.py
python_strip_whitespace/functions/regex_patterns/alpinejs.py
python_strip_whitespace/functions/regex_patterns/html.py
python_strip_whitespace/html/__init__.py
python_strip_whitespace/html/html_minifier.py
python_strip_whitespace/html/line_break.py
python_strip_whitespace/html/nbsp_characters.py
python_strip_whitespace/minify.py
python_strip_whitespace-0.1.1.dist-info/LICENSE
python_strip_whitespace-0.1.1.dist-info/METADATA
python_strip_whitespace-0.1.1.dist-info/WHEEL
python_strip_whitespace-0.1.1.dist-info/RECORD
