Metadata-Version: 2.1
Name: python-strip-whitespace
Version: 0.1.1
Summary: A powerful HTML whitespace remover for python
License: GPLv3
Author: baseplate-admin
Author-email: 61817579+baseplate-admin@users.noreply.github.com
Requires-Python: >=3.7,<4.0
Classifier: License :: Other/Proprietary License
Classifier: Programming Language :: Python :: 3
Classifier: Programming Language :: Python :: 3.7
Classifier: Programming Language :: Python :: 3.8
Classifier: Programming Language :: Python :: 3.9
Classifier: Programming Language :: Python :: 3.10
Classifier: Programming Language :: Python :: 3.11
Requires-Dist: minify-html (>=0.10.8,<0.11.0)
